prediktor/__init__.py
prediktor/interface.py
prediktor-0.1.1.dist-info/WHEEL
prediktor-0.1.1.dist-info/METADATA
prediktor-0.1.1.dist-info/RECORD
